{
  "project_info": {
    "project_number": "1006032951550",
    "project_id": "builditbigger-paid"
  },
  "client": [
    {
      "client_info": {
        "mobilesdk_app_id": "1:1006032951550:android:107db16fae3cca9d",
        "android_client_info": {
          "package_name": "com.udacity.gradle.builditbigger.paid"
        }
      },
      "oauth_client": [],
      "api_key": [
        {
          "current_key": "AIzaSyBvtzdCzKp4Pg93apaBqvtyUOMKpfz0WRA"
        }
      ],
      "services": {
        "analytics_service": {
          "status": 1
        },
        "appinvite_service": {
          "status": 1,
          "other_platform_oauth_client": []
        },
        "ads_service": {
          "status": 1
        }
      }
    }
  ],
  "configuration_version": "1"
}